servicelogging/__init__.py
servicelogging/__main__.py
servicelogging/version.py
servicelogging/tests/__init__.py
servicelogging/tests/test_servicelogging.py
service_logging-0.1.1.dist-info/LICENSE
service_logging-0.1.1.dist-info/METADATA
service_logging-0.1.1.dist-info/WHEEL
service_logging-0.1.1.dist-info/entry_points.txt
service_logging-0.1.1.dist-info/top_level.txt
service_logging-0.1.1.dist-info/RECORD
