Metadata-Version: 2.1
Name: service-logging
Version: 0.1.1
Summary: Python logging configurations done The Right Way for programs that may run in the foreground or background
Home-page: https://github.com/rpatterson/service-logging
Author: Ross Patterson
Author-email: me@rpatterson.net
License: MIT
Keywords: logging syslog nteventlog console
Platform: UNKNOWN
Classifier: Development Status :: 4 - Beta
Classifier: Environment :: Console
Classifier: Intended Audience :: Developers
Classifier: Intended Audience :: System Administrators
Classifier: License :: OSI Approved :: MIT License
Classifier: Natural Language :: English
Classifier: Operating System :: OS Independent
Classifier: Programming Language :: Python
Classifier: Topic :: System :: Logging
Classifier: Topic :: Utilities
Requires-Python: >=2.7
Requires-Dist: main-wrapper
Provides-Extra: dev
Requires-Dist: six ; extra == 'dev'
Requires-Dist: pytest ; extra == 'dev'
Requires-Dist: pre-commit ; extra == 'dev'
Requires-Dist: coverage ; extra == 'dev'
Requires-Dist: flake8 ; extra == 'dev'
Requires-Dist: autoflake ; extra == 'dev'
Requires-Dist: autopep8 ; extra == 'dev'
Requires-Dist: rstcheck ; extra == 'dev'
Requires-Dist: contextlib2 ; (python_version < "3") and extra == 'dev'
Requires-Dist: pathlib2 ; (python_version < "3") and extra == 'dev'
Requires-Dist: flake8-black ; (python_version >= "3") and extra == 'dev'
Provides-Extra: loguru
Requires-Dist: loguru ; (python_version >= "3") and extra == 'loguru'
